pathfinder2e_stats/__init__.py
pathfinder2e_stats/accessors.py
pathfinder2e_stats/bonuses.py
pathfinder2e_stats/check.py
pathfinder2e_stats/config.py
pathfinder2e_stats/damage.py
pathfinder2e_stats/damage_spec.py
pathfinder2e_stats/dice.py
pathfinder2e_stats/py.typed
pathfinder2e_stats/tools.py
pathfinder2e_stats/_tables/DC_adjustments.csv
pathfinder2e_stats/_tables/__init__.py
pathfinder2e_stats/_tables/earn_income.csv
pathfinder2e_stats/_tables/simple_DCs.csv
pathfinder2e_stats/_tables/NPC/2-01-abilities.csv
pathfinder2e_stats/_tables/NPC/2-02-saving_throws.csv
pathfinder2e_stats/_tables/NPC/2-03-perception.csv
pathfinder2e_stats/_tables/NPC/2-03-skills.csv
pathfinder2e_stats/_tables/NPC/2-05-AC.csv
pathfinder2e_stats/_tables/NPC/2-07-HP.csv
pathfinder2e_stats/_tables/NPC/2-09-strike_attack.csv
pathfinder2e_stats/_tables/NPC/2-10-strike_damage_dice.csv
pathfinder2e_stats/_tables/NPC/2-10-strike_damage_mean.csv
pathfinder2e_stats/_tables/NPC/2-11-spell_DC.csv
pathfinder2e_stats/_tables/NPC/2-11-spell_attack.csv
pathfinder2e_stats/_tables/NPC/2-12-area_damage_dice.csv
pathfinder2e_stats/_tables/NPC/2-12-area_damage_mean.csv
pathfinder2e_stats/_tables/NPC/2-8-resistances.csv
pathfinder2e_stats/_tables/NPC/__init__.py
pathfinder2e_stats/_tables/PC/__init__.py
pathfinder2e_stats/_tables/PC/_common.py
pathfinder2e_stats/_tables/PC/_templates.csv
pathfinder2e_stats/_tables/PC/ability_bonus.csv
pathfinder2e_stats/_tables/PC/ability_bonus.py
pathfinder2e_stats/_tables/PC/attack_item_bonus.csv
pathfinder2e_stats/_tables/PC/class_proficiency.csv
pathfinder2e_stats/_tables/PC/class_proficiency.py
pathfinder2e_stats/_tables/PC/polymorph_attack.csv
pathfinder2e_stats/_tables/PC/rage.csv
pathfinder2e_stats/_tables/PC/rage.py
pathfinder2e_stats/_tables/PC/skill_item_bonus.csv
pathfinder2e_stats/_tables/PC/skill_proficiency.csv
pathfinder2e_stats/_tables/PC/skill_proficiency.py
pathfinder2e_stats/_tables/PC/spell_proficiency.csv
pathfinder2e_stats/_tables/PC/spell_proficiency.py
pathfinder2e_stats-0.2.0.dist-info/licenses/LICENSE
pathfinder2e_stats-0.2.0.dist-info/METADATA
pathfinder2e_stats-0.2.0.dist-info/WHEEL
pathfinder2e_stats-0.2.0.dist-info/top_level.txt
pathfinder2e_stats-0.2.0.dist-info/RECORD
