Metadata-Version: 2.4
Name: pathfinder2e-stats
Version: 0.2.0
Summary: Statistical tools for Pathfinder and Starfinder 2nd edition
Author-email: Guido Imperiale <crusaderky@gmail.com>
License-Expression: Apache-2.0
Project-URL: homepage, https://github.com/crusaderky/pathfinder2e_stats
Project-URL: issues, https://github.com/crusaderky/pathfinder2e_stats/issues
Project-URL: documentation, https://pathfinder2e-stats.readthedocs.io/
Project-URL: changelog, https://pathfinder2e-stats.readthedocs.io/en/latest/whats-new.html
Keywords: pathfinder,starfinder,paizo,statistics,TTRPG,tabletop,board games
Classifier: Development Status :: 3 - Alpha
Classifier: Operating System :: OS Independent
Classifier: Topic :: Games/Entertainment :: Board Games
Classifier: Programming Language :: Python
Classifier: Programming Language :: Python :: 3
Classifier: Programming Language :: Python :: 3 :: Only
Classifier: Programming Language :: Python :: 3.11
Classifier: Programming Language :: Python :: 3.12
Classifier: Programming Language :: Python :: 3.13
Classifier: Programming Language :: Python :: 3.14
Classifier: Programming Language :: Python :: Free Threading :: 2 - Beta
Requires-Python: >=3.11
License-File: LICENSE
Requires-Dist: numpy>=1.24
Requires-Dist: pandas>=2.1
Requires-Dist: xarray>=2024.10.0
Dynamic: license-file
